{
    "title": "Marketing & BizDev",
    "createdAt": {
        "$numberInt": "154514"
    },
    "byMember": {
        "id": "m103",
        "fullname": "Nachum Yosef",
        "imgUrl": "https://res.cloudinary.com/dewuvivl4/image/upload/v1663251745/samples/people/m103_uq4dcr.jpg"
    },
    "labels": [
        {
            "title": "Presentation",
            "color": "#9aadbb",
            "id": "l101"
        },
        {
            "title": "Meeting",
            "color": "#0086c0",
            "id": "l102"
        },
        {
            "title": "With Team",
            "color": "#9d99b9",
            "id": "l103"
        },
        {
            "title": "",
            "color": "#d1d1d1",
            "id": "lDefault"
        }
    ],
    "status": [
        {
            "title": "Done",
            "color": "#00c876",
            "id": "s101"
        },
        {
            "title": "Working on it",
            "color": "#fdab3d",
            "id": "s102"
        },
        {
            "title": "Stuck",
            "color": "#e2445c",
            "id": "s103"
        },
        {
            "title": "",
            "color": "#d1d1d1",
            "id": "sDefault"
        }
    ],
    "priority": [
        {
            "title": "Critical",
            "color": "#333333",
            "id": "p101"
        },
        {
            "title": "High",
            "color": "#401694",
            "id": "p102"
        },
        {
            "title": "Medium",
            "color": "#5559df",
            "id": "p103"
        },
        {
            "title": "Low",
            "color": "#579bfc",
            "id": "p104"
        },
        {
            "title": "",
            "color": "#d1d1d1",
            "id": "pDefault"
        }
    ],
    "members": [
        {
            "id": "m101",
            "name": "Robert Susan",
            "email": "shiran@gmail.com",
            "isAdmin": false,
            "joinedAt": {
                "$numberDouble": "1.6582915145650E+12"
            },
            "lastSeen": {
                "$numberDouble": "1.6582915145650E+12"
            },
            "imgUrl": "https://res.cloudinary.com/dewuvivl4/image/upload/v1663251746/samples/people/m101_jvvppz.jpg",
            "color": "#f5f5f5"
        },
        {
            "id": "m102",
            "name": "Ashley Mark",
            "email": "Meital@gmail.com",
            "isAdmin": false,
            "joinedAt": {
                "$numberDouble": "1.6582915145650E+12"
            },
            "lastSeen": {
                "$numberDouble": "1.6582915145650E+12"
            },
            "imgUrl": "https://res.cloudinary.com/dewuvivl4/image/upload/v1663251746/samples/people/m102_urthuq.jpg",
            "color": "#f5f5f5"
        },
        {
            "id": "m103",
            "name": "Nachum Yosef",
            "email": "Nachum@gmail.com",
            "isAdmin": true,
            "joinedAt": {
                "$numberDouble": "1.6582915145650E+12"
            },
            "lastSeen": {
                "$numberDouble": "1.6582915145650E+12"
            },
            "imgUrl": "https://res.cloudinary.com/dewuvivl4/image/upload/v1663251745/samples/people/m103_uq4dcr.jpg",
            "color": "#f5f5f5"
        },
        {
            "id": "m104",
            "name": "Carol Paul",
            "email": "Tal@gmail.com",
            "isAdmin": false,
            "joinedAt": {
                "$numberDouble": "1.6582915145650E+12"
            },
            "lastSeen": {
                "$numberDouble": "1.6582915145650E+12"
            },
            "imgUrl": "https://res.cloudinary.com/dewuvivl4/image/upload/v1663251746/samples/people/m104_ghlqgu.jpg",
            "color": "#f5f5f5"
        }
    ],
    "colsOrder": [
        {
            "title": "Item",
            "type": "item"
        },
        {
            "title": "Text",
            "type": "textCmp"
        },
        {
            "title": "person",
            "type": "person"
        },
        {
            "title": "date",
            "type": "date"
        },
        {
            "title": "label",
            "type": "labelCmp"
        },
        {
            "title": "status",
            "type": "status"
        },
        {
            "title": "priority",
            "type": "priority"
        },
        {
            "title": "location",
            "type": "location"
        },
        {
            "title": "creation log",
            "type": "creationLog"
        }
    ],
    "groups": [
        {
            "isCollapse": false,
            "title": "BizDev",
            "color": "#a25ddc",
            "tasks": [
                {
                    "id": "HZ702",
                    "cols": [
                        {
                            "type": "item",
                            "value": "with Viola"
                        },
                        {
                            "type": "creationLog",
                            "value": {
                                "$numberDouble": "1.6593467042740E+12"
                            }
                        },
                        {
                            "type": "date",
                            "value": {
                                "$numberDouble": "1.6595604000000E+12"
                            }
                        },
                        {
                            "type": "person",
                            "value": [
                                {
                                    "id": "m102",
                                    "fullname": "Ashley Mark",
                                    "imgUrl": "https://res.cloudinary.com/dewuvivl4/image/upload/v1663251746/samples/people/m102_urthuq.jpg"
                                }
                            ]
                        },
                        {
                            "type": "textCmp",
                            "value": "Kanban Collab"
                        },
                        {
                            "type": "status",
                            "value": "s102"
                        },
                        {
                            "type": "labelCmp",
                            "value": "l101"
                        },
                        {
                            "type": "priority",
                            "value": "p101"
                        },
                        {
                            "type": "location",
                            "value": {
                                "title": "Nahalat Binyamin St",
                                "lnglat": {
                                    "lat": {
                                        "$numberDouble": "32.059662"
                                    },
                                    "lng": {
                                        "$numberDouble": "34.772449"
                                    }
                                }
                            }
                        }
                    ],
                    "isDone": false,
                    "createdAt": {
                        "$numberDouble": "1.6593467042740E+12"
                    },
                    "createdBy": {
                        "id": "m101",
                        "name": "Robert Susan",
                        "email": "shiran@gmail.com",
                        "isAdmin": false,
                        "joinedAt": {
                            "$numberDouble": "1.6582915145650E+12"
                        },
                        "lastSeen": {
                            "$numberDouble": "1.6582915145650E+12"
                        },
                        "imgUrl": "https://res.cloudinary.com/dewuvivl4/image/upload/v1663251746/samples/people/m101_jvvppz.jpg",
                        "color": "#f5f5f5"
                    },
                    "groupId": "v0aWZ"
                },
                {
                    "id": "PkSu9",
                    "cols": [
                        {
                            "type": "item",
                            "value": "with Trello.com"
                        },
                        {
                            "type": "creationLog",
                            "value": {
                                "$numberDouble": "1.6593478977730E+12"
                            }
                        },
                        {
                            "type": "date",
                            "value": {
                                "$numberDouble": "1.6605972000000E+12"
                            }
                        },
                        {
                            "type": "person",
                            "value": [
                                {
                                    "id": "m101",
                                    "fullname": "Robert Susan",
                                    "imgUrl": "https://res.cloudinary.com/dewuvivl4/image/upload/v1663251746/samples/people/m101_jvvppz.jpg"
                                },
                                {
                                    "id": "m104",
                                    "fullname": "Carol Paul",
                                    "imgUrl": "https://res.cloudinary.com/dewuvivl4/image/upload/v1663251746/samples/people/m104_ghlqgu.jpg"
                                }
                            ]
                        },
                        {
                            "type": "textCmp",
                            "value": "Increasing Storage"
                        },
                        {
                            "type": "status",
                            "value": "s101"
                        },
                        {
                            "type": "labelCmp",
                            "value": "l102"
                        },
                        {
                            "type": "priority",
                            "value": "p102"
                        },
                        {
                            "type": "location",
                            "value": {
                                "title": "HaArba'a St",
                                "lnglat": {
                                    "lat": {
                                        "$numberDouble": "32.070418"
                                    },
                                    "lng": {
                                        "$numberDouble": "34.781"
                                    }
                                }
                            }
                        }
                    ],
                    "isDone": false,
                    "createdAt": {
                        "$numberDouble": "1.6593478977740E+12"
                    },
                    "createdBy": {
                        "id": "m102",
                        "name": "Ashley Mark",
                        "email": "Meital@gmail.com",
                        "isAdmin": true,
                        "joinedAt": {
                            "$numberDouble": "1.6582915145650E+12"
                        },
                        "lastSeen": {
                            "$numberDouble": "1.6582915145650E+12"
                        },
                        "imgUrl": "https://res.cloudinary.com/dewuvivl4/image/upload/v1663251746/samples/people/m102_urthuq.jpg",
                        "color": "#f5f5f5"
                    },
                    "groupId": "v0aWZ"
                }
            ],
            "id": "v0aWZ"
        },
        {
            "isCollapse": false,
            "title": "Events",
            "color": "#fb642e",
            "tasks": [
                {
                    "id": "M167M",
                    "cols": [
                        {
                            "type": "item",
                            "value": "HighTech Summit in HK"
                        },
                        {
                            "type": "creationLog",
                            "value": {
                                "$numberDouble": "1.6593481094380E+12"
                            }
                        },
                        {
                            "type": "date",
                            "value": {
                                "$numberDouble": "1.6643988000000E+12"
                            }
                        },
                        {
                            "type": "person",
                            "value": [
                                {
                                    "id": "m101",
                                    "fullname": "Robert Susan",
                                    "imgUrl": "https://res.cloudinary.com/dewuvivl4/image/upload/v1663251746/samples/people/m101_jvvppz.jpg"
                                },
                                {
                                    "id": "m102",
                                    "fullname": "Ashley Mark",
                                    "imgUrl": "https://res.cloudinary.com/dewuvivl4/image/upload/v1663251746/samples/people/m102_urthuq.jpg"
                                },
                                {
                                    "id": "m104",
                                    "fullname": "Carol Paul",
                                    "imgUrl": "https://res.cloudinary.com/dewuvivl4/image/upload/v1663251746/samples/people/m104_ghlqgu.jpg"
                                }
                            ]
                        },
                        {
                            "type": "textCmp",
                            "value": "Entering the Chinese market"
                        },
                        {
                            "type": "status",
                            "value": "s102"
                        },
                        {
                            "type": "labelCmp",
                            "value": "l101"
                        },
                        {
                            "type": "priority",
                            "value": "p102"
                        },
                        {
                            "type": "location",
                            "value": {
                                "title": "HK",
                                "lnglat": {
                                    "lat": {
                                        "$numberDouble": "22.3193039"
                                    },
                                    "lng": {
                                        "$numberDouble": "114.1693611"
                                    }
                                }
                            }
                        }
                    ],
                    "isDone": false,
                    "createdAt": {
                        "$numberDouble": "1.6593481094380E+12"
                    },
                    "createdBy": {
                        "id": "m101",
                        "name": "Robert Susan",
                        "email": "shiran@gmail.com",
                        "isAdmin": false,
                        "joinedAt": {
                            "$numberDouble": "1.6582915145650E+12"
                        },
                        "lastSeen": {
                            "$numberDouble": "1.6582915145650E+12"
                        },
                        "imgUrl": "https://res.cloudinary.com/dewuvivl4/image/upload/v1663251746/samples/people/m101_jvvppz.jpg",
                        "color": "#f5f5f5"
                    },
                    "groupId": "WvOMK"
                },
                {
                    "id": "Vagbe",
                    "cols": [
                        {
                            "type": "item",
                            "value": "Tech 12 High-Tech Conference"
                        },
                        {
                            "type": "creationLog",
                            "value": {
                                "$numberDouble": "1.6593481617050E+12"
                            }
                        },
                        {
                            "type": "date",
                            "value": {
                                "$numberDouble": "1.6620660000000E+12"
                            }
                        },
                        {
                            "type": "person",
                            "value": [
                                {
                                    "id": "m101",
                                    "fullname": "Robert Susan",
                                    "imgUrl": "https://res.cloudinary.com/dewuvivl4/image/upload/v1663251746/samples/people/m101_jvvppz.jpg"
                                },
                                {
                                    "id": "m102",
                                    "fullname": "Ashley Mark",
                                    "imgUrl": "https://res.cloudinary.com/dewuvivl4/image/upload/v1663251746/samples/people/m102_urthuq.jpg"
                                }
                            ]
                        },
                        {
                            "type": "textCmp",
                            "value": null
                        },
                        {
                            "type": "status",
                            "value": "s101"
                        },
                        {
                            "type": "labelCmp",
                            "value": "l103"
                        },
                        {
                            "type": "priority",
                            "value": "p103"
                        },
                        {
                            "type": "location",
                            "value": {
                                "title": "Azrieli Center",
                                "lnglat": {
                                    "lat": {
                                        "$numberDouble": "32.0740769"
                                    },
                                    "lng": {
                                        "$numberDouble": "34.7922028"
                                    }
                                }
                            }
                        }
                    ],
                    "isDone": false,
                    "createdAt": {
                        "$numberDouble": "1.6593481617050E+12"
                    },
                    "createdBy": {
                        "id": "m102",
                        "name": "Ashley Mark",
                        "email": "Meital@gmail.com",
                        "isAdmin": true,
                        "joinedAt": {
                            "$numberDouble": "1.6582915145650E+12"
                        },
                        "lastSeen": {
                            "$numberDouble": "1.6582915145650E+12"
                        },
                        "imgUrl": "",
                        "color": "#f5f5f5"
                    },
                    "groupId": "WvOMK"
                },
                {
                    "id": "9GPyh",
                    "cols": [
                        {
                            "type": "item",
                            "value": "Startup for Startup Podcast"
                        },
                        {
                            "type": "creationLog",
                            "value": {
                                "$numberDouble": "1.6593482116770E+12"
                            }
                        },
                        {
                            "type": "date",
                            "value": {
                                "$numberDouble": "1.6602516000000E+12"
                            }
                        },
                        {
                            "type": "person",
                            "value": [
                                {
                                    "id": "m101",
                                    "fullname": "Robert Susan",
                                    "imgUrl": "https://res.cloudinary.com/dewuvivl4/image/upload/v1663251746/samples/people/m101_jvvppz.jpg"
                                },
                                {
                                    "id": "m102",
                                    "fullname": "Ashley Mark",
                                    "imgUrl": "https://res.cloudinary.com/dewuvivl4/image/upload/v1663251746/samples/people/m102_urthuq.jpg"
                                }
                            ]
                        },
                        {
                            "type": "textCmp",
                            "value": null
                        },
                        {
                            "type": "status",
                            "value": "sDefault"
                        },
                        {
                            "type": "labelCmp",
                            "value": "l103"
                        },
                        {
                            "type": "priority",
                            "value": "p104"
                        },
                        {
                            "type": "location",
                            "value": {
                                "title": "Herzliya Pituah",
                                "lnglat": {
                                    "lat": {
                                        "$numberDouble": "32.174202"
                                    },
                                    "lng": {
                                        "$numberDouble": "34.802932"
                                    }
                                }
                            }
                        }
                    ],
                    "isDone": false,
                    "createdAt": {
                        "$numberDouble": "1.6593482116770E+12"
                    },
                    "createdBy": {
                        "id": "m104",
                        "name": "Carol Paul",
                        "email": "Tal@gmail.com",
                        "isAdmin": false,
                        "joinedAt": {
                            "$numberDouble": "1.6582915145650E+12"
                        },
                        "lastSeen": {
                            "$numberDouble": "1.6582915145650E+12"
                        },
                        "imgUrl": "https://res.cloudinary.com/dewuvivl4/image/upload/v1663251746/samples/people/m104_ghlqgu.jpg",
                        "color": "#f5f5f5"
                    },
                    "groupId": "WvOMK"
                },
                {
                    "id": "CRFO1",
                    "cols": [
                        {
                            "type": "item",
                            "value": "SheCodes Hackaton"
                        },
                        {
                            "type": "creationLog",
                            "value": {
                                "$numberDouble": "1.6593482525200E+12"
                            }
                        },
                        {
                            "type": "date",
                            "value": {
                                "$numberDouble": "1.6618932000000E+12"
                            }
                        },
                        {
                            "type": "person",
                            "value": [
                                {
                                    "id": "m104",
                                    "fullname": "Carol Paul",
                                    "imgUrl": "https://res.cloudinary.com/dewuvivl4/image/upload/v1663251746/samples/people/m104_ghlqgu.jpg"
                                }
                            ]
                        },
                        {
                            "type": "textCmp",
                            "value": null
                        },
                        {
                            "type": "status",
                            "value": "sDefault"
                        },
                        {
                            "type": "labelCmp",
                            "value": "l102"
                        },
                        {
                            "type": "priority",
                            "value": "p102"
                        },
                        {
                            "type": "location",
                            "value": null
                        }
                    ],
                    "isDone": false,
                    "createdAt": {
                        "$numberDouble": "1.6593482525200E+12"
                    },
                    "createdBy": {
                        "id": "m102",
                        "name": "Ashley Mark",
                        "email": "Meital@gmail.com",
                        "isAdmin": true,
                        "joinedAt": {
                            "$numberDouble": "1.6582915145650E+12"
                        },
                        "lastSeen": {
                            "$numberDouble": "1.6582915145650E+12"
                        },
                        "imgUrl": "https://res.cloudinary.com/dewuvivl4/image/upload/v1663251746/samples/people/m102_urthuq.jpg",
                        "color": "#f5f5f5"
                    },
                    "groupId": "WvOMK"
                },
                {
                    "id": "WJ9iz",
                    "cols": [
                        {
                            "type": "item",
                            "value": "Coding Academy Apps&Beer"
                        },
                        {
                            "type": "creationLog",
                            "value": {
                                "$numberDouble": "1.6593483483600E+12"
                            }
                        },
                        {
                            "type": "date",
                            "value": {
                                "$numberDouble": "1.6593876000000E+12"
                            }
                        },
                        {
                            "type": "person",
                            "value": [
                                {
                                    "id": "m101",
                                    "fullname": "Robert Susan",
                                    "imgUrl": "https://res.cloudinary.com/dewuvivl4/image/upload/v1663251746/samples/people/m101_jvvppz.jpg"
                                },
                                {
                                    "id": "m102",
                                    "fullname": "Ashley Mark",
                                    "imgUrl": "https://res.cloudinary.com/dewuvivl4/image/upload/v1663251746/samples/people/m102_urthuq.jpg"
                                },
                                {
                                    "id": "m104",
                                    "fullname": "Carol Paul",
                                    "imgUrl": "https://res.cloudinary.com/dewuvivl4/image/upload/v1663251746/samples/people/m104_ghlqgu.jpg"
                                }
                            ]
                        },
                        {
                            "type": "textCmp",
                            "value": null
                        },
                        {
                            "type": "status",
                            "value": "s102"
                        },
                        {
                            "type": "labelCmp",
                            "value": "l102"
                        },
                        {
                            "type": "priority",
                            "value": "p102"
                        },
                        {
                            "type": "location",
                            "value": null
                        }
                    ],
                    "isDone": false,
                    "createdAt": {
                        "$numberDouble": "1.6593483483600E+12"
                    },
                    "createdBy": {
                        "id": "m104",
                        "name": "Carol Paul",
                        "email": "Tal@gmail.com",
                        "isAdmin": false,
                        "joinedAt": {
                            "$numberDouble": "1.6582915145650E+12"
                        },
                        "lastSeen": {
                            "$numberDouble": "1.6582915145650E+12"
                        },
                        "imgUrl": "https://res.cloudinary.com/dewuvivl4/image/upload/v1663251746/samples/people/m104_ghlqgu.jpg",
                        "color": "#f5f5f5"
                    },
                    "groupId": "WvOMK"
                }
            ],
            "id": "WvOMK"
        },
        {
            "isCollapse": true,
            "title": "Creative",
            "tasks": [
                {
                    "id": "efV8k",
                    "cols": [
                        {
                            "type": "item",
                            "value": "New logo Design"
                        },
                        {
                            "type": "creationLog",
                            "value": {
                                "$numberDouble": "1.6593484941820E+12"
                            }
                        },
                        {
                            "type": "date",
                            "value": {
                                "$numberDouble": "1.6643124000000E+12"
                            }
                        },
                        {
                            "type": "person",
                            "value": [
                                {
                                    "id": "m102",
                                    "fullname": "Ashley Mark",
                                    "imgUrl": "https://res.cloudinary.com/dewuvivl4/image/upload/v1663251746/samples/people/m102_urthuq.jpg"
                                },
                                {
                                    "id": "m104",
                                    "fullname": "Carol Paul",
                                    "imgUrl": "https://res.cloudinary.com/dewuvivl4/image/upload/v1663251746/samples/people/m104_ghlqgu.jpg"
                                }
                            ]
                        },
                        {
                            "type": "textCmp",
                            "value": null
                        },
                        {
                            "type": "status",
                            "value": "s102"
                        },
                        {
                            "type": "labelCmp",
                            "value": "l103"
                        },
                        {
                            "type": "priority",
                            "value": "p101"
                        },
                        {
                            "type": "location",
                            "value": null
                        }
                    ],
                    "isDone": false,
                    "createdAt": {
                        "$numberDouble": "1.6593484941820E+12"
                    },
                    "createdBy": {
                        "id": "m101",
                        "name": "Robert Susan",
                        "email": "shiran@gmail.com",
                        "isAdmin": false,
                        "joinedAt": {
                            "$numberDouble": "1.6582915145650E+12"
                        },
                        "lastSeen": {
                            "$numberDouble": "1.6582915145650E+12"
                        },
                        "imgUrl": "https://res.cloudinary.com/dewuvivl4/image/upload/v1663251746/samples/people/m101_jvvppz.jpg",
                        "color": "#f5f5f5"
                    },
                    "groupId": "02zcN"
                },
                {
                    "id": "cdS34",
                    "cols": [
                        {
                            "type": "item",
                            "value": "Wolt collab Teaser"
                        },
                        {
                            "type": "creationLog",
                            "value": {
                                "$numberDouble": "1.6593485371550E+12"
                            }
                        },
                        {
                            "type": "date",
                            "value": {
                                "$numberDouble": "1.6618932000000E+12"
                            }
                        },
                        {
                            "type": "person",
                            "value": [
                                {
                                    "id": "m102",
                                    "fullname": "Ashley Mark",
                                    "imgUrl": "https://res.cloudinary.com/dewuvivl4/image/upload/v1663251746/samples/people/m102_urthuq.jpg"
                                },
                                {
                                    "id": "m101",
                                    "fullname": "Robert Susan",
                                    "imgUrl": "https://res.cloudinary.com/dewuvivl4/image/upload/v1663251746/samples/people/m101_jvvppz.jpg"
                                }
                            ]
                        },
                        {
                            "type": "textCmp",
                            "value": "Internal Ad"
                        },
                        {
                            "type": "status",
                            "value": "s101"
                        },
                        {
                            "type": "labelCmp",
                            "value": "l103"
                        },
                        {
                            "type": "priority",
                            "value": "p102"
                        },
                        {
                            "type": "location",
                            "value": null
                        }
                    ],
                    "isDone": false,
                    "createdAt": {
                        "$numberDouble": "1.6593485371550E+12"
                    },
                    "createdBy": {
                        "id": "m104",
                        "name": "Carol Paul",
                        "email": "Tal@gmail.com",
                        "isAdmin": false,
                        "joinedAt": {
                            "$numberDouble": "1.6582915145650E+12"
                        },
                        "lastSeen": {
                            "$numberDouble": "1.6582915145650E+12"
                        },
                        "imgUrl": "https://res.cloudinary.com/dewuvivl4/image/upload/v1663251746/samples/people/m104_ghlqgu.jpg",
                        "color": "#f5f5f5"
                    },
                    "groupId": "02zcN"
                },
                {
                    "id": "bSJkB",
                    "cols": [
                        {
                            "type": "item",
                            "value": "Facebook Campaign Ad"
                        },
                        {
                            "type": "creationLog",
                            "value": {
                                "$numberDouble": "1.6593485687360E+12"
                            }
                        },
                        {
                            "type": "date",
                            "value": {
                                "$numberDouble": "1.6616340000000E+12"
                            }
                        },
                        {
                            "type": "person",
                            "value": [
                                {
                                    "id": "m101",
                                    "fullname": "Robert Susan",
                                    "imgUrl": "https://res.cloudinary.com/dewuvivl4/image/upload/v1663251746/samples/people/m101_jvvppz.jpg"
                                }
                            ]
                        },
                        {
                            "type": "textCmp",
                            "value": null
                        },
                        {
                            "type": "status",
                            "value": "s102"
                        },
                        {
                            "type": "labelCmp",
                            "value": "l101"
                        },
                        {
                            "type": "priority",
                            "value": "p102"
                        },
                        {
                            "type": "location",
                            "value": {
                                "title": "Hod Hasharon",
                                "lnglat": {
                                    "lat": {
                                        "$numberDouble": "32.149961"
                                    },
                                    "lng": {
                                        "$numberDouble": "34.8838788"
                                    }
                                }
                            }
                        }
                    ],
                    "isDone": false,
                    "createdAt": {
                        "$numberDouble": "1.6593485687360E+12"
                    },
                    "createdBy": {
                        "id": "m101",
                        "name": "Robert Susan",
                        "email": "shiran@gmail.com",
                        "isAdmin": false,
                        "joinedAt": {
                            "$numberDouble": "1.6582915145650E+12"
                        },
                        "lastSeen": {
                            "$numberDouble": "1.6582915145650E+12"
                        },
                        "imgUrl": "https://res.cloudinary.com/dewuvivl4/image/upload/v1663251746/samples/people/m101_jvvppz.jpg",
                        "color": "#f5f5f5"
                    },
                    "groupId": "02zcN"
                },
                {
                    "id": "9s7jt",
                    "cols": [
                        {
                            "type": "item",
                            "value": "Calcalist Ad"
                        },
                        {
                            "type": "creationLog",
                            "value": {
                                "$numberDouble": "1.6593488422300E+12"
                            }
                        },
                        {
                            "type": "date",
                            "value": null
                        },
                        {
                            "type": "person",
                            "value": [
                                {
                                    "id": "m104",
                                    "fullname": "Carol Paul",
                                    "imgUrl": "https://res.cloudinary.com/dewuvivl4/image/upload/v1663251746/samples/people/m104_ghlqgu.jpg"
                                }
                            ]
                        },
                        {
                            "type": "textCmp",
                            "value": null
                        },
                        {
                            "type": "status",
                            "value": "s103"
                        },
                        {
                            "type": "labelCmp",
                            "value": "l102"
                        },
                        {
                            "type": "priority",
                            "value": "p103"
                        },
                        {
                            "type": "location",
                            "value": {
                                "title": "Ramat Hasharon",
                                "lnglat": {
                                    "lat": {
                                        "$numberDouble": "32.137793"
                                    },
                                    "lng": {
                                        "$numberDouble": "34.840278"
                                    }
                                }
                            }
                        }
                    ],
                    "isDone": false,
                    "createdAt": {
                        "$numberDouble": "1.6593488422300E+12"
                    },
                    "createdBy": {
                        "id": "m102",
                        "name": "Ashley Mark",
                        "email": "Meital@gmail.com",
                        "isAdmin": true,
                        "joinedAt": {
                            "$numberDouble": "1.6582915145650E+12"
                        },
                        "lastSeen": {
                            "$numberDouble": "1.6582915145650E+12"
                        },
                        "imgUrl": "https://res.cloudinary.com/dewuvivl4/image/upload/v1663251746/samples/people/m102_urthuq.jpg",
                        "color": "#f5f5f5"
                    },
                    "groupId": "02zcN"
                }
            ],
            "id": "02zcN",
            "color": "#227f4c"
        }
    ]
}